bendu.py
bendu-1.0.2.dist-info/LICENSE.md
bendu-1.0.2.dist-info/METADATA
bendu-1.0.2.dist-info/WHEEL
bendu-1.0.2.dist-info/entry_points.txt
bendu-1.0.2.dist-info/top_level.txt
bendu-1.0.2.dist-info/RECORD
