Metadata-Version: 2.1
Name: bendu
Version: 1.0.2
Summary: A tool automating operations with docker containers
Home-page: UNKNOWN
Author: Thodoris Mavroeidakos
License: UNKNOWN
Project-URL: Docker Project, https://github.com/tmavroeid/bendu
Platform: UNKNOWN
Classifier: Intended Audience :: Developers
Classifier: Topic :: Software Development :: Build Tools
Classifier: License :: OSI Approved :: MIT License
Classifier: Programming Language :: Python :: 3
Requires-Python: >=3.7, <4
Requires-Dist: click
Requires-Dist: docker
Requires-Dist: requests
